crczp/terraform_driver/__init__.py
crczp/terraform_driver/terraform_backend.py
crczp/terraform_driver/terraform_client.py
crczp/terraform_driver/terraform_client_elements.py
crczp/terraform_driver/terraform_client_manager.py
crczp/terraform_driver/terraform_exc_handlers.py
crczp/terraform_driver/terraform_exceptions.py
crczp/terraform_driver/templates/terraform_backend.j2
crczp_terraform_client-1.0.2.dist-info/METADATA
crczp_terraform_client-1.0.2.dist-info/WHEEL
crczp_terraform_client-1.0.2.dist-info/licenses/LICENSE
crczp_terraform_client-1.0.2.dist-info/RECORD
